lib/libnvqir-QuantumRingsLib.so
quantumrings_toolkit_cudaq-0.10.2100.dist-info/licenses/LICENSE.rst
targets/QuantumRingsLib.yml
quantumrings_toolkit_cudaq-0.10.2100.dist-info/METADATA
quantumrings_toolkit_cudaq-0.10.2100.dist-info/WHEEL
quantumrings_toolkit_cudaq-0.10.2100.dist-info/top_level.txt
quantumrings_toolkit_cudaq-0.10.2100.dist-info/RECORD
