Metadata-Version: 2.4
Name: quantumrings-toolkit-cudaq
Version: 0.10.2100
Summary: Quantum Rings toolkit for CUDA-Q
Author-email: "Quantum Rings Inc." <contact@quantumrings.com>
Project-URL: Homepage, https://www.quantumrings.com/docs
Project-URL: Documentation, https://www.quantumrings.com/docs
Project-URL: API Reference, https://quantumrings.com/doc/modules.html
Keywords: quantum,quantum circuit,quantum computing,quantum programming language,quantum register,quantum tools,cuda,gpu,cudaq,tools,sdk
Classifier: Development Status :: 3 - Alpha
Classifier: Environment :: Console
Classifier: Intended Audience :: Developers
Classifier: Intended Audience :: Science/Research
Classifier: Topic :: Software Development :: Build Tools
Classifier: Topic :: Scientific/Engineering
Classifier: Programming Language :: Python
Classifier: Operating System :: POSIX :: Linux
License-File: LICENSE.rst
Requires-Dist: cudaq>=0.10.0
Dynamic: license-file
